repo_find_orphans/__init__.py
repo_find_orphans/cli.py
repo_find_orphans/manifest.py
repo_find_orphans/py.typed
repo_find_orphans/remote.py
repo_find_orphans/scan.py
repo_find_orphans/selections.py
repo_find_orphans/types/__init__.py
repo_find_orphans/types/project.py
repo_find_orphans/types/remote.py
repo_find_orphans-0.1.2.dist-info/LICENSE
repo_find_orphans-0.1.2.dist-info/METADATA
repo_find_orphans-0.1.2.dist-info/WHEEL
repo_find_orphans-0.1.2.dist-info/entry_points.txt
repo_find_orphans-0.1.2.dist-info/RECORD
