Metadata-Version: 2.1
Name: repo-find-orphans
Version: 0.1.2
Summary: Supplements to the repo script
Author: Vlad
Author-email: vlad@v-lad.org
Requires-Python: >=3.11.0,<4.0.0
Classifier: Development Status :: 4 - Beta
Classifier: Environment :: Console
Classifier: Intended Audience :: Developers
Classifier: License :: OSI Approved :: MIT License
Classifier: Operating System :: OS Independent
Classifier: Programming Language :: Python :: 3
Classifier: Programming Language :: Python :: 3.11
Classifier: Programming Language :: Python :: 3.12
Classifier: Topic :: Software Development
Classifier: Topic :: Software Development :: Version Control
Classifier: Topic :: Software Development :: Version Control :: Git
Classifier: Topic :: Utilities
Classifier: Typing :: Typed
Requires-Dist: annotated-types (>=0.6.0,<0.7.0)
Requires-Dist: defusedxml (>=0.7.1,<0.8.0)
Requires-Dist: pygithub (>=2.3.0,<3.0.0)
Requires-Dist: pyyaml (>=6.0.1,<7.0.0)
Requires-Dist: typer (>=0.12.3,<0.13.0)
Requires-Dist: types-pyyaml (>=6.0.12.20240311,<7.0.0.0)
